python_course_by_ty/__init__.py
python_course_by_ty/python_course.py
python_course_by_ty-0.2.2.dist-info/METADATA
python_course_by_ty-0.2.2.dist-info/WHEEL
python_course_by_ty-0.2.2.dist-info/top_level.txt
python_course_by_ty-0.2.2.dist-info/RECORD
